README.rst
setup.cfg
setup.py
skitaid/__init__.py
skitaid.egg-info/PKG-INFO
skitaid.egg-info/SOURCES.txt
skitaid.egg-info/dependency_links.txt
skitaid.egg-info/requires.txt
skitaid.egg-info/top_level.txt
skitaid/bin/install_win32_service.py
skitaid/bin/skitaid-cron.py
skitaid/bin/skitaid-instance.py
skitaid/bin/skitaid-smtpda.py
skitaid/bin/skitaid.py
skitaid/etc/init/skitaid.conf
skitaid/etc/init.d/skitaid
skitaid/etc/skitaid/skitaid.conf
skitaid/etc/skitaid/certifications/README.txt
skitaid/etc/skitaid/certifications/example.key
skitaid/etc/skitaid/certifications/example.pem
skitaid/etc/skitaid/servers-available/README.txt
skitaid/etc/skitaid/servers-enabled-nt/example.conf
skitaid/etc/skitaid/servers-enabled-posix/example.conf
skitaid/wsgi/example/app.py
skitaid/wsgi/example/app_single_thread.py
skitaid/wsgi/example/auth.py
skitaid/wsgi/example/gateway.py
skitaid/wsgi/example/grpc_route_guide.py
skitaid/wsgi/example/jinja2overlay.py
skitaid/wsgi/example/proxy.py
skitaid/wsgi/example/reverse_proxy.py
skitaid/wsgi/example/rpc2.py
skitaid/wsgi/example/tls12.py
skitaid/wsgi/example/websocket-flask.py
skitaid/wsgi/example/websocket.py
skitaid/wsgi/example/apppackages/__init__.py
skitaid/wsgi/example/apppackages/route_guide_pb2.py
skitaid/wsgi/example/resources/sqlite3.db
skitaid/wsgi/example/static/reindeer.jpg
skitaid/wsgi/example/templates/documentation.html
skitaid/wsgi/example/templates/documentation2.html
skitaid/wsgi/example/templates/index.html
skitaid/wsgi/example/templates/jinja2overlay.html
skitaid/wsgi/example/templates/websocket-flask.html
skitaid/wsgi/example/templates/websocket.html