Metadata-Version: 1.1
Name: skitaid
Version: 0.8.8.3
Summary: Skitai App Engine Daemon
Home-page: https://gitlab.com/hansroh/skitaid
Author: Hans Roh
Author-email: hansroh@gmail.com
License: MIT
Download-URL: https://pypi.python.org/pypi/skitaid
Platform: posix
Platform: nt
Classifier: License :: OSI Approved :: MIT License
Classifier: Development Status :: 4 - Beta
Classifier: Topic :: Internet :: WWW/HTTP
Classifier: Topic :: Internet :: WWW/HTTP :: HTTP Servers
Classifier: Environment :: Console
Classifier: Environment :: No Input/Output (Daemon)
Classifier: Topic :: Software Development :: Libraries :: Python Modules
Classifier: Intended Audience :: Developers
Classifier: Intended Audience :: Science/Research
Classifier: Programming Language :: Python
Classifier: Programming Language :: Python :: 2.7
Classifier: Programming Language :: Python :: 3
